shirley/__init__.py
shirley/clients/__init__.py
shirley/clients/chat.py
shirley/clients/client.py
shirley/clients/tts.py
shirley/interfaces/__init__.py
shirley/interfaces/chat.py
shirley/interfaces/footer.py
shirley/interfaces/header.py
shirley/interfaces/interface.py
shirley/interfaces/tts.py
shirley/options/__init__.py
shirley/options/client.py
shirley/options/components.py
shirley/options/interfaces.py
shirley/types/__init__.py
shirley/utils/__init__.py
shirley/utils/pickleablegenerator.py
shirley-0.1.19.dist-info/LICENSE
shirley-0.1.19.dist-info/METADATA
shirley-0.1.19.dist-info/WHEEL
shirley-0.1.19.dist-info/entry_points.txt
shirley-0.1.19.dist-info/RECORD
