Metadata-Version: 2.1
Name: shirley
Version: 0.1.19
Summary: It is just doing some stuff intelligently.
Author: luojiahai
Author-email: luo@jiahai.co
Requires-Python: ==3.10.*
Classifier: Programming Language :: Python :: 3
Classifier: Programming Language :: Python :: 3.10
Requires-Dist: azure-cognitiveservices-speech (>=1.38.0,<2.0.0)
Requires-Dist: einops (>=0.8.0,<0.9.0)
Requires-Dist: gradio (>=4.39.0,<5.0.0)
Requires-Dist: numpy (==1.26.4)
Requires-Dist: pypdf (>=4.3.1,<5.0.0)
Requires-Dist: pytest (>=8.3.1,<9.0.0)
Requires-Dist: tiktoken (>=0.7.0,<0.8.0)
Requires-Dist: transformers (==4.36.0)
Requires-Dist: transformers-stream-generator (>=0.0.5,<0.0.6)
